flask_fastrpc.py
Flask_FastRPC-1.5.dist-info/DESCRIPTION.rst
Flask_FastRPC-1.5.dist-info/METADATA
Flask_FastRPC-1.5.dist-info/RECORD
Flask_FastRPC-1.5.dist-info/WHEEL
Flask_FastRPC-1.5.dist-info/metadata.json
Flask_FastRPC-1.5.dist-info/top_level.txt
