Metadata-Version: 2.0
Name: Flask-FastRPC
Version: 1.5
Summary: Flask extension for FastRPC/XMLRPC server
Home-page: https://github.com/iScrE4m/Flask-FastRPC
Author: David Jetelina
Author-email: david.jetelina@firma.seznam.cz
License: BSD
Platform: any
Classifier: Environment :: Web Environment
Classifier: Intended Audience :: Developers
Classifier: License :: OSI Approved :: BSD License
Classifier: Operating System :: OS Independent
Classifier: Programming Language :: Python
Classifier: Programming Language :: Python :: 3 :: Only
Classifier: Topic :: Internet :: WWW/HTTP :: Dynamic Content
Classifier: Topic :: Software Development :: Libraries :: Python Modules
Requires-Dist: Flask
Requires-Dist: typeguard
